noterpy/__init__.py
noterpy/noter.py
noterpy-0.1.1.dist-info/DESCRIPTION.rst
noterpy-0.1.1.dist-info/METADATA
noterpy-0.1.1.dist-info/RECORD
noterpy-0.1.1.dist-info/WHEEL
noterpy-0.1.1.dist-info/metadata.json
noterpy-0.1.1.dist-info/top_level.txt
tests/__init__.py
tests/test_noter.py
