Metadata-Version: 2.0
Name: noterpy
Version: 0.1.1
Summary: A python client for SimpleNote (simplenote.com)
Home-page: https://github.com/SlapBot/noterpy
Author: Ujjwal Gupta
Author-email: ugupta41@gmail.com
License: MIT
Keywords: noterpy pynoter simplenote simplenote.com note api-client noter notes
Platform: UNKNOWN
Classifier: Development Status :: 3 - Alpha
Classifier: Environment :: Web Environment
Classifier: Operating System :: OS Independent
Classifier: Intended Audience :: Developers
Classifier: Topic :: Software Development :: Build Tools
Classifier: License :: OSI Approved :: MIT License
Classifier: Programming Language :: Python
Classifier: Programming Language :: Python :: 3
Classifier: Programming Language :: Python :: 3.3
Classifier: Programming Language :: Python :: 3.4
Classifier: Programming Language :: Python :: 3.5
Requires-Dist: simplenote
